cubed4th/FORTH.py
cubed4th/__init__.py
cubed4th/cli_FORTH.py
cubed4th/doc_FORTH.py
cubed4th/WORDS/F_CHAINS.py
cubed4th/WORDS/F_CONTROL.py
cubed4th/WORDS/F_CORE.py
cubed4th/WORDS/F_CURSES.py
cubed4th/WORDS/F_ECDSA.py
cubed4th/WORDS/F_HASHES.py
cubed4th/WORDS/F_HTTPS.py
cubed4th/WORDS/F_INPUT.py
cubed4th/WORDS/F_JSON.py
cubed4th/WORDS/F_MATH.py
cubed4th/WORDS/F_OBJECT.py
cubed4th/WORDS/F_OUTPUT.py
cubed4th/WORDS/F_REPL.py
cubed4th/WORDS/F_STACK.py
cubed4th/WORDS/F_UNICODE.py
cubed4th/WORDS/F_XML.py
cubed4th/WORDS/__init__.py
globals/__init__.py
t18e-0.0.0.dist-info/LICENCES.md
t18e-0.0.0.dist-info/METADATA
t18e-0.0.0.dist-info/WHEEL
t18e-0.0.0.dist-info/entry_points.txt
t18e-0.0.0.dist-info/top_level.txt
t18e-0.0.0.dist-info/RECORD
